LICENSE
MANIFEST.in
README.rst
setup.py
srcgen/__init__.py
srcgen/base.py
srcgen/c.py
srcgen/html.py
srcgen/js.py
srcgen/python.py
srcgen/version.py
srcgen.egg-info/PKG-INFO
srcgen.egg-info/SOURCES.txt
srcgen.egg-info/dependency_links.txt
srcgen.egg-info/requires.txt
srcgen.egg-info/top_level.txt