Metadata-Version: 1.1
Name: srcgen
Version: 1.1.0
Summary: srcgen: The semantic source code generation framework
Home-page: https://srcgen.readthedocs.org/
Author: Tomer Filiba
Author-email: tomerfiliba@gmail.com
License: MIT
Keywords: source,code,generation,programmatic,semantic
Platform: UNKNOWN
Classifier: Development Status :: 5 - Production/Stable
Classifier: License :: OSI Approved :: MIT License
Classifier: Programming Language :: Python :: 2.5
Classifier: Programming Language :: Python :: 2.6
Classifier: Programming Language :: Python :: 2.7
Classifier: Programming Language :: Python :: 3
Classifier: Programming Language :: Python :: 3.0
Classifier: Programming Language :: Python :: 3.1
Classifier: Programming Language :: Python :: 3.2
Classifier: Programming Language :: Python :: 3.3
Provides: srcgen
